vuer/__init__.py
vuer/base.py
vuer/events.py
vuer/schemas.py
vuer/serdes.py
vuer/server.py
vuer/types.py
vuer/__pycache__/__init__.cpython-38.pyc
vuer/__pycache__/base.cpython-38.pyc
vuer/__pycache__/events.cpython-38.pyc
vuer/__pycache__/schemas.cpython-38.pyc
vuer/__pycache__/serdes.cpython-38.pyc
vuer/__pycache__/server.cpython-38.pyc
vuer/addons/__init__.py
vuer/addons/nerf_vuer/__init__.py
vuer/addons/nerf_vuer/control_components.py
vuer/addons/nerf_vuer/mixins.py
vuer/addons/nerf_vuer/nerf_vuer.py
vuer/addons/nerf_vuer/render_components.py
vuer/addons/nerf_vuer/render_nodes.py
vuer/addons/nerfuer/__init__.py
vuer/addons/nerfuer/render_nodes.py
vuer-0.1.0.dist-info/LICENSE
vuer-0.1.0.dist-info/METADATA
vuer-0.1.0.dist-info/WHEEL
vuer-0.1.0.dist-info/entry_points.txt
vuer-0.1.0.dist-info/top_level.txt
vuer-0.1.0.dist-info/RECORD
