Metadata-Version: 2.1
Name: vuer
Version: 0.1.0
Home-page: https://github.com/geyang/vuer
Author: Ge Yang<ge.ike.yang@gmail.com>
Author-email: ge.ike.yang@gmail.com
License: MIT
Classifier: Development Status :: 3 - Alpha
Classifier: Programming Language :: Python
Requires-Python: >=3.8.6
License-File: LICENSE
Requires-Dist: tqdm
Requires-Dist: termcolor
Requires-Dist: trimesh
Requires-Dist: numpy
Requires-Dist: params-proto
Requires-Dist: killport
Requires-Dist: msgpack
Requires-Dist: websockets
Requires-Dist: aiohttp
Requires-Dist: aiohttp-cors
Requires-Dist: pillow
Provides-Extra: dev
Requires-Dist: black ==22.3.0 ; extra == 'dev'
Requires-Dist: pylint ==2.13.4 ; extra == 'dev'
Requires-Dist: pytest ==7.1.2 ; extra == 'dev'
